<?xml version="1.0" encoding="UTF-8"?><chunk xmlns="http://www.infinitaslearning.com/namespaces/ICoM" class="html-book-text" id="978-9-147-10385-0_SOS_Geo_imageexport-Sec612-7-2-text"><chunk-body xmlns:css="http://www.w3.org/1996/css" xmlns:icom="http://www.infinitaslearning.com/namespaces/ICoM" xmlns:xlink="http://www.w3.org/1999/xlink" xmlns:tr="http://transpect.io"><p>Metangas och olika typer av kväveoxider är kraftfulla växthusgaser, men halterna i atmosfären av dessa gaser är ganska låga. Metan är 20 gånger effektivare som växthusgas jämfört med koldioxid. Metangasen bildas vid nedbrytning av framförallt växter, och de största bidragen kommer från jordbruket. Kossor rapar metan, och i risfält som står under vatten bildas mycket metan. Men även från gasledningar och utvinning av naturgas läcker en del ut i atmosfären.</p><!--unsuppressed--><div class="concept"><p>Visste du att</p><p>halterna av koldioxid och metan i atmosfären är högre än de varit på 650 000 år.</p></div><p>När temperaturen ökar i Arktis kommer den djupfrysta tundran att tina. I tundran finns enorma mängder infrusen metan som kommer att läcka ut i atmosfären.</p></chunk-body></chunk>