<?xml version="1.0" encoding="UTF-8"?><chunk xmlns="http://www.infinitaslearning.com/namespaces/ICoM" class="html-book-text" id="978-9-147-10385-0_SOS_Geo_imageexport-Sec624-6-8-text"><chunk-body xmlns:css="http://www.w3.org/1996/css" xmlns:icom="http://www.infinitaslearning.com/namespaces/ICoM" xmlns:xlink="http://www.w3.org/1999/xlink" xmlns:tr="http://transpect.io"><p>När jorden blir varmare stiger havsytan. Risken för översvämningar av länder med låga kuster ökar. Nederländerna planerar redan att bygga på sina fördämningar och vallar mot Nordsjön. Värre är det för fattiga länder som Bangladesh, där det saknas pengar till att bygga vallar. Problemen kommer också att öka vid stormar och orkaner. När havets nivå är högre kommer också översvämningarna som hänger ihop med ovädren att bli värre.</p><!--unsuppressed--><div class="fact"><p class="title">När isen smälter</p><p>Om alla glaciärer och inlands­isar smälte bort skulle havs­ytan stiga med 60 meter.</p></div><p>Många av jordens största städer, som New York, Buenos Aires, Tokyo, Hong Kong och Calcutta, ligger vid havet och där måste man redan nu planera för en ökad risk för översvämningar.</p><p>Men värst är nog ändå krisen för de låga öarna i Indiska oceanen och Stilla havet som bara sticker upp någon meter över havsytan. Dessa öar bildades en gång vid vulkanutbrott på havsbottnen, men själva vulkanen har under miljontals år nötts ner av vågor, väder och vind. Nu består öarna av låga korallrev som byggts upp kring de slocknade vulkanerna. Om hundra år kan de flesta öarna vara dränkta av havet.</p><object id="Sec624-image-299" mimetype="image/png" idref="SOS_Geografi_0308_9789147103850_art_r1"/><!--suppressed,  sec1--></chunk-body></chunk>