<?xml version="1.0" encoding="UTF-8"?><chunk xmlns="http://www.infinitaslearning.com/namespaces/ICoM" class="html-book-text" id="978-9-147-10385-0_SOS_Geo_imageexport-Sec475-6-1-summary"><chunk-body xmlns:css="http://www.w3.org/1996/css" xmlns:icom="http://www.infinitaslearning.com/namespaces/ICoM" xmlns:xlink="http://www.w3.org/1999/xlink" xmlns:tr="http://transpect.io"><p>De tre viktigaste energikällorna för världen är olja, kol och naturgas.</p><p>Olja är den mest använda energikällan i världen.</p><p>I u-länderna använder många människor mycket lite energi i sitt dagliga liv.</p><p>Oljelandet Norge får stora inkomster genom att exportera olja och gas.</p><p>Sverige och Finland är de enda länderna i Norden som har kärnkraft.</p></chunk-body></chunk>